{
  "$schema": "https://developer.microsoft.com/json-schemas/fabric/item/report/definition/visualContainer/2.5.0/schema.json",
  "name": "6ad63a6170c382ef2377",
  "position": {
    "x": 0,
    "y": 0,
    "z": 0,
    "height": 346,
    "width": 572,
    "tabOrder": 14026
  },
  "visual": {
    "visualType": "htmlContent443BE3AD55E043BF878BED274D3A6855",
    "query": {
      "queryState": {
        "content": {
          "projections": [
            {
              "field": {
                "Measure": {
                  "Expression": {
                    "SourceRef": {
                      "Entity": "Medidas"
                    }
                  },
                  "Property": "Tutorial_Balão_3_"
                }
              },
              "queryRef": "Medidas.Tutorial_Balão_3_",
              "nativeQueryRef": "Tutorial_Balão_3_"
            }
          ]
        }
      },
      "sortDefinition": {
        "isDefaultSort": true
      }
    },
    "visualContainerObjects": {
      "background": [
        {
          "properties": {
            "show": {
              "expr": {
                "Literal": {
                  "Value": "false"
                }
              }
            }
          }
        }
      ],
      "visualHeader": [
        {
          "properties": {
            "show": {
              "expr": {
                "Literal": {
                  "Value": "false"
                }
              }
            }
          }
        }
      ],
      "visualTooltip": [
        {
          "properties": {
            "show": {
              "expr": {
                "Literal": {
                  "Value": "false"
                }
              }
            }
          }
        }
      ]
    },
    "drillFilterOtherVisuals": true
  },
  "parentGroupName": "7c17465e7210e916920c"
}